PaperSorter/__init__.py
PaperSorter/__main__.py
PaperSorter/embedding_database.py
PaperSorter/feed_database.py
PaperSorter/log.py
PaperSorter/contrib/__init__.py
PaperSorter/contrib/tor.py
PaperSorter/providers/__init__.py
PaperSorter/providers/theoldreader.py
PaperSorter/tasks/__init__.py
PaperSorter/tasks/broadcast.py
PaperSorter/tasks/feedback.py
PaperSorter/tasks/init.py
PaperSorter/tasks/train.py
PaperSorter/tasks/update.py
papersorter-0.2.dist-info/LICENSE.txt
papersorter-0.2.dist-info/METADATA
papersorter-0.2.dist-info/WHEEL
papersorter-0.2.dist-info/entry_points.txt
papersorter-0.2.dist-info/top_level.txt
papersorter-0.2.dist-info/RECORD
