Metadata-Version: 2.1
Name: papersorter
Version: 0.2
Summary: Filters RSS feeds, predicts interest, and notifies Slack with top academic articles.
Home-page: https://github.com/ChangLabSNU/papersorter
Download-URL: https://github.com/ChangLabSNU/papersorter/releases
Author: Hyeshik Chang
Author-email: hyeshik@snu.ac.kr
License: MIT
Keywords: article alerts,RSS feed,personalized content
Classifier: Development Status :: 3 - Alpha
Classifier: Environment :: Console
Classifier: Intended Audience :: Education
Classifier: Intended Audience :: Science/Research
Classifier: License :: OSI Approved :: MIT License
Classifier: Operating System :: POSIX
Classifier: Topic :: Office/Business :: News/Diary
Classifier: Topic :: Text Processing :: Linguistic
Classifier: Topic :: Scientific/Engineering
License-File: LICENSE.txt
Requires-Dist: click >=8.0
Requires-Dist: numpy >=1.20
Requires-Dist: openai >=1.30
Requires-Dist: pandas >=2.0
Requires-Dist: plyvel >=1.5
Requires-Dist: python-dotenv >=1.0
Requires-Dist: requests >=2.7.0
Requires-Dist: scikit-learn >=1.4
Requires-Dist: scipy >=1.10
Requires-Dist: xgboost >2.0
Requires-Dist: xlsxwriter >=3.0
